optopenhash/__init__.py
optopenhash/elastic_hashing.py
optopenhash/funnel_hashing.py
tests/__init__.py
tests/test_tables.py
optopenhash-0.2.0.dist-info/LICENSE
optopenhash-0.2.0.dist-info/METADATA
optopenhash-0.2.0.dist-info/WHEEL
optopenhash-0.2.0.dist-info/top_level.txt
optopenhash-0.2.0.dist-info/RECORD
