Metadata-Version: 2.2
Name: optopenhash
Version: 0.2.0
Summary: A Python package implementing improved open‐addressing hash tables based on the paper "Optimal Bounds for Open Addressing Without Reordering".
Home-page: https://github.com/sternma/optopenhash
Author: Matthew Stern
Author-email: matthew.stern@ztsystems.com
Classifier: Programming Language :: Python :: 3
Classifier: Operating System :: OS Independent
Requires-Python: >=3.6
License-File: LICENSE
Dynamic: author
Dynamic: author-email
Dynamic: classifier
Dynamic: description
Dynamic: description-content-type
Dynamic: home-page
Dynamic: requires-python
Dynamic: summary
